{"title":"아이보스 ─ 뉴스 ─ 전체보기","url":"https://www.i-boss.co.kr/ab-7214","favicon":"https://www.i-boss.co.kr/favicon.ico","elements":[{"title":"[9월 16일 마케팅 뉴스클리핑] 유튜브, 공짜로 영상 보려면 광고 5개 봐 외","contents":"막내운영자","link":"https://www.i-boss.co.kr/ab-2877-9511","retrieved":1663284226913},{"title":"크래프톤 버추얼 휴먼 ‘애나(ANA)’, 첫 디지털 싱글 공개","contents":"cookiman","link":"https://www.i-boss.co.kr/ab-2877-9510","retrieved":1663217335379},{"title":"고프로, 히어로11 블랙 국내 정식 출시... \"역대 최고의 촬영 환경 제공\"","contents":"cookiman","link":"https://www.i-boss.co.kr/ab-2877-9509","retrieved":1663217335380},{"title":"국립중앙박물관, 올 가을 ‘MZ세대 놀이터’로 변신하다","contents":"cookiman","link":"https://www.i-boss.co.kr/ab-2877-9508","retrieved":1663217335395},{"title":"더에스엠씨그룹, 네이버 브랜드 커넥트 서비스 협력사 선정","contents":"cookiman","link":"https://www.i-boss.co.kr/ab-2877-9507","retrieved":1663207844885},{"title":"로블록스, 2023년부터 게임 내 광고 허용","contents":"막내운영자","link":"https://www.i-boss.co.kr/ab-2877-9505","retrieved":1663207844885},{"title":"\"추워져도 Y2K 인기는 지속된다\"... 에이블리, 가을 패션 트렌드 공개","contents":"cookiman","link":"https://www.i-boss.co.kr/ab-2877-9506","retrieved":1663207844885},{"title":"지금은 제로(Zero)의 시대! 설탕, 쓰레기, 칼로리를 줄이자","contents":"cookiman","link":"https://www.i-boss.co.kr/ab-2877-9504","retrieved":1663207844885},{"title":"[트렌드 모니터] 요즘 가족, 책임감 남았지만 유대감 희미해져...","contents":"cookiman","link":"https://www.i-boss.co.kr/ab-2877-9503","retrieved":1663207844885},{"title":"익숙함에 새로움을 더한다... 유통업계, MZ세대가 즐겨보는 유튜브 활용한 ‘뉴클래식’ 마케팅 펼치다","contents":"cookiman","link":"https://www.i-boss.co.kr/ab-2877-9502","retrieved":1663207844885},{"title":"[9월 15일 마케팅 뉴스클리핑] 네이버 스마트스토어, 6년간 49만 개... 연평균 37% 증가 외","contents":"막내운영자","link":"https://www.i-boss.co.kr/ab-2877-9501","retrieved":1663197705624},{"title":"인스타그램, 크리에이터 수익화 기능 '기프트' 테스트","contents":"막내운영자","link":"https://www.i-boss.co.kr/ab-2877-9500","retrieved":1663129278354},{"title":"SSG닷컴, 오픈마켓 종료... 이베이 중복 사업 정리","contents":"막내운영자","link":"https://www.i-boss.co.kr/ab-2877-9499","retrieved":1663120902293},{"title":"CJ올리브네트웍스 x 비마이프렌즈, 크리에이터 이코노미 생태계 확장에 나선다","contents":"cookiman","link":"https://www.i-boss.co.kr/ab-2877-9498","retrieved":1663120902294},{"title":"몰로코, ‘2022 Inc. 5000’ 리스트 선정","contents":"cookiman","link":"https://www.i-boss.co.kr/ab-2877-9497","retrieved":1663120902296},{"title":"[인포그래픽] 마케팅에서의 색채 심리학","contents":"cookiman","link":"https://www.i-boss.co.kr/ab-2877-9496","retrieved":1663120902306},{"title":"[신인섭 칼럼] '고(古)인쇄박물관' 주최 한국 광고 전시회가 주는 시사","contents":"cookiman","link":"https://www.i-boss.co.kr/ab-2877-9495","retrieved":1663120902306},{"title":"[9월 14일 마케팅 뉴스클리핑] 인스타그램, 피드서 '리포스트' 기능 도입 검토 외","contents":"막내운영자","link":"https://www.i-boss.co.kr/ab-2877-9493","retrieved":1663111820613},{"title":"한국PR협회, \"숏폼 영상 콘텐츠\"를 주제로 김용태 더에스엠씨그룹 대표와 권기정 호프만에이전시코리아 대표 PR 토크 개최","contents":"cookiman","link":"https://www.i-boss.co.kr/ab-2877-9494","retrieved":1663060952689},{"title":"발란, 사전·사후 감정 강화한 '발란 케어' 출시","contents":"막내운영자","link":"https://www.i-boss.co.kr/ab-2877-9492","retrieved":1663054705350},{"title":"한국인이 가장 많이 사용하는 전문몰 앱은?","contents":"막내운영자","link":"https://www.i-boss.co.kr/ab-2877-9491","retrieved":1663034831404},{"title":"신중년, 제주에 가면 \"이 호텔\"에 묵고 싶다","contents":"cookiman","link":"https://www.i-boss.co.kr/ab-2877-9490","retrieved":1663034831409},{"title":"[해외 크리에이티브] 캔디 크러쉬 사가, 10주년을 축하하다","contents":"cookiman","link":"https://www.i-boss.co.kr/ab-2877-9489","retrieved":1663034831409},{"title":"[Tip!] 추적해야 할 소셜 미디어 KPI","contents":"cookiman","link":"https://www.i-boss.co.kr/ab-2877-9488","retrieved":1663034831409},{"title":"[9월 13일 마케팅 뉴스클리핑] 네이버 영수증 리뷰 이벤트 종료 외","contents":"막내운영자","link":"https://www.i-boss.co.kr/ab-2877-9487","retrieved":1663024996824},{"title":"[해외 크리에이티브] 울마크 컴퍼니, 기름으로 채워진 수영장으로 패션의 환경적 현실을 드러내다","contents":"cookiman","link":"https://www.i-boss.co.kr/ab-2877-9486","retrieved":1662948651861},{"title":"마더, 방탄 레저웨어로 커머스 사업 론칭","contents":"cookiman","link":"https://www.i-boss.co.kr/ab-2877-9485","retrieved":1662948651863},{"title":"플라스틱 물병이 다이아몬드로 바뀐다고?","contents":"cookiman","link":"https://www.i-boss.co.kr/ab-2877-9484","retrieved":1662948651864},{"title":"[인포그래픽] 1993년 이후 가장 인기 있는 웹사이트","contents":"cookiman","link":"https://www.i-boss.co.kr/ab-2877-9483","retrieved":1662948651866},{"title":"[박재항의 反轉 커뮤니케이션] 모든 아기는 왕자나 공주이다","contents":"cookiman","link":"https://www.i-boss.co.kr/ab-2877-9482","retrieved":1662948651867}]}